tensorlogic/__init__.py
tensorlogic/py.typed
tensorlogic/api/__init__.py
tensorlogic/api/compiler.py
tensorlogic/api/errors.py
tensorlogic/api/parser.py
tensorlogic/api/patterns.py
tensorlogic/api/validation.py
tensorlogic/backends/__init__.py
tensorlogic/backends/cuda.py
tensorlogic/backends/factory.py
tensorlogic/backends/mlx.py
tensorlogic/backends/numpy.py
tensorlogic/backends/protocol.py
tensorlogic/backends/sparse.py
tensorlogic/compilation/__init__.py
tensorlogic/compilation/factory.py
tensorlogic/compilation/protocol.py
tensorlogic/compilation/strategies/__init__.py
tensorlogic/compilation/strategies/godel.py
tensorlogic/compilation/strategies/hard.py
tensorlogic/compilation/strategies/lukasiewicz.py
tensorlogic/compilation/strategies/product.py
tensorlogic/compilation/strategies/soft.py
tensorlogic/core/__init__.py
tensorlogic/core/composition.py
tensorlogic/core/operations.py
tensorlogic/core/quantifiers.py
tensorlogic/core/temperature.py
tensorlogic/integrations/__init__.py
tensorlogic/integrations/langchain/__init__.py
tensorlogic/integrations/langchain/retriever.py
tensorlogic/integrations/rag/__init__.py
tensorlogic/integrations/rag/constraints.py
tensorlogic/integrations/rag/ranker.py
tensorlogic/integrations/rag/retriever.py
tensorlogic/verification/__init__.py
tensorlogic/verification/lean_bridge.py
tensorlogic/verification/results.py
tensorlogic/verification/theorems.py
python_tensorlogic-0.3.5.dist-info/METADATA
python_tensorlogic-0.3.5.dist-info/WHEEL
python_tensorlogic-0.3.5.dist-info/licenses/LICENSE
python_tensorlogic-0.3.5.dist-info/RECORD
