Metadata-Version: 2.4
Name: python-tensorlogic
Version: 0.3.5
Summary: Neural-symbolic AI framework unifying logical reasoning and tensor computation
Project-URL: Homepage, https://github.com/Mathews-Tom/TensorLogic
Project-URL: Documentation, https://github.com/Mathews-Tom/TensorLogic#readme
Project-URL: Repository, https://github.com/Mathews-Tom/TensorLogic.git
Project-URL: Issues, https://github.com/Mathews-Tom/TensorLogic/issues
Project-URL: Changelog, https://github.com/Mathews-Tom/TensorLogic/releases
Author: TensorLogic Contributors
License: MIT
License-File: LICENSE
Keywords: ai,logic,mlx,neural-symbolic,reasoning,tensor
Classifier: Development Status :: 3 - Alpha
Classifier: Intended Audience :: Developers
Classifier: Intended Audience :: Science/Research
Classifier: License :: OSI Approved :: MIT License
Classifier: Programming Language :: Python :: 3
Classifier: Programming Language :: Python :: 3.12
Classifier: Topic :: Scientific/Engineering :: Artificial Intelligence
Classifier: Typing :: Typed
Requires-Python: >=3.12
Requires-Dist: numpy>=1.24.0
Provides-Extra: all
Requires-Dist: mlx>=0.30.0; extra == 'all'
Requires-Dist: scipy>=1.11.0; extra == 'all'
Provides-Extra: colab
Requires-Dist: cupy-cuda12x>=13.0.0; extra == 'colab'
Requires-Dist: scipy>=1.11.0; extra == 'colab'
Provides-Extra: cuda
Requires-Dist: cupy-cuda12x>=13.0.0; extra == 'cuda'
Provides-Extra: cuda11
Requires-Dist: cupy-cuda11x>=13.0.0; extra == 'cuda11'
Provides-Extra: mlx
Requires-Dist: mlx>=0.30.0; extra == 'mlx'
Provides-Extra: sparse
Requires-Dist: scipy>=1.11.0; extra == 'sparse'
